neural/__init__.py
neural/py.typed
neural/analysis/__init__.py
neural/analysis/sentiment.py
neural/analysis/backtesting/engine.py
neural/analysis/execution/__init__.py
neural/analysis/execution/order_manager.py
neural/analysis/risk/__init__.py
neural/analysis/risk/position_sizing.py
neural/analysis/strategies/__init__.py
neural/analysis/strategies/arbitrage.py
neural/analysis/strategies/base.py
neural/analysis/strategies/mean_reversion.py
neural/analysis/strategies/momentum.py
neural/analysis/strategies/news_based.py
neural/analysis/strategies/sentiment_strategy.py
neural/auth/__init__.py
neural/auth/client.py
neural/auth/env.py
neural/auth/http_client.py
neural/auth/signers/__init__.py
neural/auth/signers/kalshi.py
neural/data_collection/__init__.py
neural/data_collection/aggregator.py
neural/data_collection/base.py
neural/data_collection/espn_enhanced.py
neural/data_collection/kalshi.py
neural/data_collection/kalshi_api_source.py
neural/data_collection/kalshi_historical.py
neural/data_collection/registry.py
neural/data_collection/rest_api.py
neural/data_collection/transformer.py
neural/data_collection/twitter_source.py
neural/data_collection/websocket.py
neural/trading/__init__.py
neural/trading/client.py
neural/trading/fix.py
neural/trading/fix_streaming.py
neural/trading/paper_client.py
neural/trading/paper_portfolio.py
neural/trading/paper_report.py
neural/trading/rest_streaming.py
neural/trading/websocket.py
neural_sdk-0.3.0.dist-info/licenses/LICENSE
neural_sdk-0.3.0.dist-info/METADATA
neural_sdk-0.3.0.dist-info/WHEEL
neural_sdk-0.3.0.dist-info/entry_points.txt
neural_sdk-0.3.0.dist-info/top_level.txt
neural_sdk-0.3.0.dist-info/RECORD
