Metadata-Version: 2.4
Name: neural-sdk
Version: 0.3.0
Summary: Professional-grade SDK for algorithmic trading on prediction markets (Beta - Core features stable, advanced modules experimental)
Author-email: Hudson Aikins <hudson@intelip.co>, Neural Contributors <contributors@neural-sdk.dev>
Maintainer-email: Advanced Intellectual Labs LLC <hudson@intelip.co>, Neural Contributors <contributors@neural-sdk.dev>
License-Expression: MIT
Project-URL: Homepage, https://github.com/IntelIP/Neural
Project-URL: Documentation, https://neural-sdk.mintlify.app
Project-URL: Repository, https://github.com/IntelIP/Neural
Project-URL: Issues, https://github.com/IntelIP/Neural/issues
Project-URL: Changelog, https://github.com/IntelIP/Neural/blob/main/CHANGELOG.md
Keywords: kalshi,prediction-markets,trading,algorithmic-trading,sports-betting,event-contracts,prediction-api,market-data,quantitative-finance
Classifier: Development Status :: 4 - Beta
Classifier: Intended Audience :: Developers
Classifier: Intended Audience :: Financial and Insurance Industry
Classifier: Natural Language :: English
Classifier: Operating System :: OS Independent
Classifier: Programming Language :: Python :: 3
Classifier: Programming Language :: Python :: 3.10
Classifier: Programming Language :: Python :: 3.11
Classifier: Programming Language :: Python :: 3.12
Classifier: Framework :: Pytest
Classifier: Topic :: Office/Business :: Financial :: Investment
Classifier: Topic :: Software Development :: Libraries :: Python Modules
Classifier: Topic :: Scientific/Engineering :: Information Analysis
Classifier: Topic :: Internet :: WWW/HTTP :: Dynamic Content
Classifier: Typing :: Typed
Requires-Python: >=3.10
License-File: LICENSE
Requires-Dist: requests>=2.31.0
Requires-Dist: cryptography>=41.0.0
Requires-Dist: python-dotenv>=1.0.0
Requires-Dist: kalshi-python>=2.1.4
Requires-Dist: websocket-client>=1.7.0
Requires-Dist: websockets>=11.0.0
Requires-Dist: simplefix>=1.0.17
Requires-Dist: pandas>=2.0.0
Requires-Dist: numpy<2.0,>=1.24.0
Requires-Dist: certifi>=2023.0.0
Requires-Dist: textblob>=0.17.1
Requires-Dist: vaderSentiment>=3.3.2
Requires-Dist: aiohttp>=3.8.0
Requires-Dist: plotly>=5.15.0
Provides-Extra: dev
Requires-Dist: pytest>=7.4.0; extra == "dev"
Requires-Dist: pytest-cov>=4.1.0; extra == "dev"
Requires-Dist: pytest-asyncio>=0.21.0; extra == "dev"
Requires-Dist: black>=23.7.0; extra == "dev"
Requires-Dist: ruff>=0.0.282; extra == "dev"
Requires-Dist: mypy>=1.4.1; extra == "dev"
Requires-Dist: types-requests>=2.31.0; extra == "dev"
Requires-Dist: bump2version>=1.0.0; extra == "dev"
Requires-Dist: build>=0.10.0; extra == "dev"
Requires-Dist: twine>=4.0.0; extra == "dev"
Provides-Extra: docs
Requires-Dist: mkdocs>=1.5.0; extra == "docs"
Requires-Dist: mkdocs-material>=9.1.0; extra == "docs"
Requires-Dist: mkdocstrings[python]>=0.22.0; extra == "docs"
Provides-Extra: trading
Requires-Dist: kalshi-python<3,>=2.1.4; extra == "trading"
Provides-Extra: sentiment
Requires-Dist: textblob>=0.17.1; extra == "sentiment"
Requires-Dist: vaderSentiment>=3.3.2; extra == "sentiment"
Requires-Dist: transformers>=4.21.0; extra == "sentiment"
Requires-Dist: torch>=1.12.0; extra == "sentiment"
Requires-Dist: scikit-learn>=1.1.0; extra == "sentiment"
Dynamic: license-file
